{
	"configurations" : 
	[
		{
			"directories" : 
			[
				{
					"build" : ".",
					"hasInstallRule" : true,
					"jsonFile" : "directory-.-51461ac589da28183478.json",
					"minimumCMakeVersion" : 
					{
						"string" : "3.15"
					},
					"projectIndex" : 0,
					"source" : ".",
					"targetIndexes" : 
					[
						0,
						1,
						2
					]
				}
			],
			"name" : "",
			"projects" : 
			[
				{
					"directoryIndexes" : 
					[
						0
					],
					"name" : "ros2_control_demo_example_11",
					"targetIndexes" : 
					[
						0,
						1,
						2
					]
				}
			],
			"targets" : 
			[
				{
					"directoryIndex" : 0,
					"id" : "ros2_control_demo_example_11::@6890427a1f51a3e7e1df",
					"jsonFile" : "target-ros2_control_demo_example_11-259c70d68aef8c23eb62.json",
					"name" : "ros2_control_demo_example_11",
					"projectIndex" : 0
				},
				{
					"directoryIndex" : 0,
					"id" : "ros2_control_demo_example_11_uninstall::@6890427a1f51a3e7e1df",
					"jsonFile" : "target-ros2_control_demo_example_11_uninstall-e3acbc9f21bb41de1608.json",
					"name" : "ros2_control_demo_example_11_uninstall",
					"projectIndex" : 0
				},
				{
					"directoryIndex" : 0,
					"id" : "uninstall::@6890427a1f51a3e7e1df",
					"jsonFile" : "target-uninstall-333844fc4b820b1505e8.json",
					"name" : "uninstall",
					"projectIndex" : 0
				}
			]
		}
	],
	"kind" : "codemodel",
	"paths" : 
	{
		"build" : "/workspaces/ros2-coding/build/ros2_control_demo_example_11",
		"source" : "/workspaces/ros2-coding/turtlesim_ws/src/ros-controls/ros2_control_demos/example_11"
	},
	"version" : 
	{
		"major" : 2,
		"minor" : 6
	}
}
